jac_misc/VERSION
jac_misc/__init__.py
jac_misc/config.py
jac_misc/cluster/__init__.py
jac_misc/cluster/cluster.py
jac_misc/cluster/requirements.txt
jac_misc/cluster/tests/__init__.py
jac_misc/cluster/tests/test_cluster.py
jac_misc/cluster/tests/fixtures/__init__.py
jac_misc/cluster/tests/fixtures/cluster.jac
jac_misc/elastic_retrieval/__init__.py
jac_misc/elastic_retrieval/elastic_retrieval.py
jac_misc/elastic_retrieval/requirements.txt
jac_misc/elastic_retrieval/utils.py
jac_misc/example_module/__init__.py
jac_misc/example_module/example_module.py
jac_misc/example_module/requirements.txt
jac_misc/forecast/__init__.py
jac_misc/forecast/action_utils.py
jac_misc/forecast/forecast.py
jac_misc/forecast/requirements.txt
jac_misc/forecast/tests/__init__.py
jac_misc/forecast/tests/test_forecast.py
jac_misc/huggingface/__init__.py
jac_misc/huggingface/huggingface.py
jac_misc/huggingface/requirements.txt
jac_misc/huggingface/utils.py
jac_misc/langchain/__init__.py
jac_misc/langchain/main.py
jac_misc/langchain/requirements.txt
jac_misc/openai/__init__.py
jac_misc/openai/main.py
jac_misc/openai/requirements.txt
jac_misc/pdf_ext/__init__.py
jac_misc/pdf_ext/pdf_ext.py
jac_misc/pdf_ext/requirements.txt
jac_misc/pdf_ext/tests/__init__.py
jac_misc/pdf_ext/tests/test_pdf_ext.py
jac_misc/pdf_ext/tests/fixtures/__init__.py
jac_misc/pdf_ext/tests/fixtures/pdf_ext.jac
jac_misc/ph/__init__.py
jac_misc/ph/config.yaml
jac_misc/ph/custom.py
jac_misc/ph/inference.py
jac_misc/ph/ph.py
jac_misc/ph/ph_train_data.json
jac_misc/ph/requirements.txt
jac_misc/ph/run_ph.py
jac_misc/ph/train.py
jac_misc/ph/utils/__init__.py
jac_misc/ph/utils/base.py
jac_misc/ph/utils/dataloader.py
jac_misc/ph/utils/logger.py
jac_misc/ph/utils/loss.py
jac_misc/ph/utils/metric.py
jac_misc/ph/utils/model.py
jac_misc/ph/utils/process.py
jac_misc/ph/utils/trainer.py
jac_misc/ph/utils/util.py
jac_misc/translator/__init__.py
jac_misc/translator/requirements.txt
jac_misc/translator/translator.py
jac_misc-1.4.2.6.dist-info/METADATA
jac_misc-1.4.2.6.dist-info/WHEEL
jac_misc-1.4.2.6.dist-info/top_level.txt
jac_misc-1.4.2.6.dist-info/RECORD
