Metadata-Version: 2.1
Name: jac_misc
Version: 1.4.2.6
Home-page: https://github.com/Jaseci-Labs/jaseci/jaseci_ai_kit/jac_misc
Author: Jason Mars
Author-email: jason@jaseci.org
Requires-Dist: jaseci ==1.4.2.6
Requires-Dist: pytest <7.1,>=7.0.1
Requires-Dist: pytest-order <1.1,>=1.0.1
Provides-Extra: all
Requires-Dist: pypdf ==3.15.4 ; extra == 'all'
Requires-Dist: transformers >=4.0.0 ; extra == 'all'
Requires-Dist: torch <2.0.0,>=1.10.2 ; extra == 'all'
Requires-Dist: sentencepiece ; extra == 'all'
Requires-Dist: protobuf <3.21,>=3.20.1 ; extra == 'all'
Requires-Dist: hdbscan <0.9,>=0.8.33 ; extra == 'all'
Requires-Dist: umap-learn ==0.5.3 ; extra == 'all'
Requires-Dist: scikit-learn <1.3.0 ; extra == 'all'
Requires-Dist: uuid <2.0.0,>=1.30 ; extra == 'all'
Requires-Dist: transformers >=4.25.1 ; extra == 'all'
Requires-Dist: openai ==1.3.0 ; extra == 'all'
Requires-Dist: soundfile <0.13,>=0.12.1 ; extra == 'all'
Requires-Dist: elasticsearch ==8.9.0 ; extra == 'all'
Requires-Dist: tenacity >=8.2.1 ; extra == 'all'
Requires-Dist: docx2txt >=0.8 ; extra == 'all'
Requires-Dist: python-pptx >=0.6.21 ; extra == 'all'
Requires-Dist: tiktoken >=0.2.0 ; extra == 'all'
Requires-Dist: langchain ; extra == 'all'
Requires-Dist: openai ; extra == 'all'
Requires-Dist: chromadb ; extra == 'all'
Requires-Dist: tiktoken ; extra == 'all'
Provides-Extra: cluster
Requires-Dist: hdbscan <0.9,>=0.8.33 ; extra == 'cluster'
Requires-Dist: umap-learn ==0.5.3 ; extra == 'cluster'
Requires-Dist: scikit-learn <1.3.0 ; extra == 'cluster'
Provides-Extra: elastic_retrieval
Requires-Dist: openai ==1.3.0 ; extra == 'elastic_retrieval'
Requires-Dist: elasticsearch ==8.9.0 ; extra == 'elastic_retrieval'
Requires-Dist: tenacity >=8.2.1 ; extra == 'elastic_retrieval'
Requires-Dist: PyPDF ==3.15.4 ; extra == 'elastic_retrieval'
Requires-Dist: docx2txt >=0.8 ; extra == 'elastic_retrieval'
Requires-Dist: python-pptx >=0.6.21 ; extra == 'elastic_retrieval'
Requires-Dist: tiktoken >=0.2.0 ; extra == 'elastic_retrieval'
Provides-Extra: forecast
Provides-Extra: huggingface
Provides-Extra: langchain
Requires-Dist: langchain ; extra == 'langchain'
Requires-Dist: openai ; extra == 'langchain'
Requires-Dist: chromadb ; extra == 'langchain'
Requires-Dist: tiktoken ; extra == 'langchain'
Provides-Extra: openai
Requires-Dist: openai ==1.3.0 ; extra == 'openai'
Requires-Dist: soundfile <0.13,>=0.12.1 ; extra == 'openai'
Provides-Extra: pdf_ext
Requires-Dist: pypdf ==3.15.4 ; extra == 'pdf_ext'
Provides-Extra: ph
Requires-Dist: torch <2.0.0,>=1.10.2 ; extra == 'ph'
Requires-Dist: uuid <2.0.0,>=1.30 ; extra == 'ph'
Requires-Dist: transformers >=4.25.1 ; extra == 'ph'
Provides-Extra: translator
Requires-Dist: transformers >=4.0.0 ; extra == 'translator'
Requires-Dist: torch <2.0.0,>=1.10.2 ; extra == 'translator'
Requires-Dist: sentencepiece ; extra == 'translator'
Requires-Dist: protobuf <3.21,>=3.20.1 ; extra == 'translator'
